{
    "total": [
        {
            "id": "1197123062",
            "count": 0
        },
        {
            "id": "61550031276478",
            "count": 0
        },
        {
            "id": "61550107253260",
            "count": 0
        },
        {
            "id": "61550613790223",
            "count": 0
        },
        {
            "id": "61550756554683",
            "count": 0
        },
        {
            "id": "61550816582998",
            "count": 0
        },
        {
            "id": "61550960244237",
            "count": 0
        },
        {
            "id": "61552945585289",
            "count": 0
        },
        {
            "id": "61553659281345",
            "count": 0
        },
        {
            "id": "61554417387970",
            "count": 0
        },
        {
            "id": "61554433296893",
            "count": 0
        },
        {
            "id": "61555272445621",
            "count": 0
        },
        {
            "id": "61555511198283",
            "count": 0
        },
        {
            "id": "61555650861816",
            "count": 0
        },
        {
            "id": "61556026537354",
            "count": 0
        },
        {
            "id": "61556137711909",
            "count": 0
        },
        {
            "id": "61556199785981",
            "count": 0
        },
        {
            "id": "61556430681607",
            "count": 0
        },
        {
            "id": "100001483504823",
            "count": 0
        },
        {
            "id": "100005137653837",
            "count": 0
        },
        {
            "id": "100006551203604",
            "count": 0
        },
        {
            "id": "100010890945250",
            "count": 0
        },
        {
            "id": "100013375203759",
            "count": 0
        },
        {
            "id": "100016477056398",
            "count": 0
        },
        {
            "id": "100021066455709",
            "count": 0
        },
        {
            "id": "100022709412936",
            "count": 0
        },
        {
            "id": "100022806620524",
            "count": 0
        },
        {
            "id": "100023250277879",
            "count": 0
        },
        {
            "id": "100026359569628",
            "count": 0
        },
        {
            "id": "100026981884907",
            "count": 0
        },
        {
            "id": "100027244842325",
            "count": 0
        },
        {
            "id": "100028012126633",
            "count": 0
        },
        {
            "id": "100029905974007",
            "count": 0
        },
        {
            "id": "100030166266762",
            "count": 0
        },
        {
            "id": "100030258973537",
            "count": 0
        },
        {
            "id": "100033434828918",
            "count": 0
        },
        {
            "id": "100037833782670",
            "count": 0
        },
        {
            "id": "100037905271955",
            "count": 0
        },
        {
            "id": "100038664707166",
            "count": 0
        },
        {
            "id": "100041026933257",
            "count": 0
        },
        {
            "id": "100042077481734",
            "count": 0
        },
        {
            "id": "100045955503373",
            "count": 0
        },
        {
            "id": "100046099540344",
            "count": 0
        },
        {
            "id": "100048444757243",
            "count": 0
        },
        {
            "id": "100050038279181",
            "count": 0
        },
        {
            "id": "100050224210035",
            "count": 0
        },
        {
            "id": "100051870045481",
            "count": 0
        },
        {
            "id": "100052333065163",
            "count": 0
        },
        {
            "id": "100053586144323",
            "count": 0
        },
        {
            "id": "100054496869415",
            "count": 0
        },
        {
            "id": "100054868245935",
            "count": 0
        },
        {
            "id": "100054870732307",
            "count": 0
        },
        {
            "id": "100056426214479",
            "count": 0
        },
        {
            "id": "100056702887203",
            "count": 0
        },
        {
            "id": "100056745708577",
            "count": 0
        },
        {
            "id": "100058606900376",
            "count": 0
        },
        {
            "id": "100058970956271",
            "count": 0
        },
        {
            "id": "100059906962202",
            "count": 0
        },
        {
            "id": "100060035434807",
            "count": 0
        },
        {
            "id": "100060779195213",
            "count": 0
        },
        {
            "id": "100060923303072",
            "count": 0
        },
        {
            "id": "100061212372279",
            "count": 0
        },
        {
            "id": "100061638674575",
            "count": 0
        },
        {
            "id": "100061681069898",
            "count": 1
        },
        {
            "id": "100062591730134",
            "count": 0
        },
        {
            "id": "100063600891672",
            "count": 0
        },
        {
            "id": "100063773742944",
            "count": 0
        },
        {
            "id": "100065116733444",
            "count": 0
        },
        {
            "id": "100065302164449",
            "count": 0
        },
        {
            "id": "100066073701917",
            "count": 0
        },
        {
            "id": "100066228437034",
            "count": 0
        },
        {
            "id": "100067377774776",
            "count": 0
        },
        {
            "id": "100067463912717",
            "count": 0
        },
        {
            "id": "100069877930512",
            "count": 0
        },
        {
            "id": "100072122673872",
            "count": 0
        },
        {
            "id": "100072603382299",
            "count": 0
        },
        {
            "id": "100072994342483",
            "count": 0
        },
        {
            "id": "100073119091740",
            "count": 0
        },
        {
            "id": "100073603485750",
            "count": 0
        },
        {
            "id": "100073655200260",
            "count": 0
        },
        {
            "id": "100073786282614",
            "count": 0
        },
        {
            "id": "100074331896453",
            "count": 0
        },
        {
            "id": "100074720064406",
            "count": 0
        },
        {
            "id": "100075398285629",
            "count": 0
        },
        {
            "id": "100075401613274",
            "count": 0
        },
        {
            "id": "100075509484911",
            "count": 0
        },
        {
            "id": "100076240372790",
            "count": 0
        },
        {
            "id": "100076614848111",
            "count": 0
        },
        {
            "id": "100077099160173",
            "count": 0
        },
        {
            "id": "100077129421074",
            "count": 0
        },
        {
            "id": "100077532079160",
            "count": 0
        },
        {
            "id": "100077725557978",
            "count": 0
        },
        {
            "id": "100078187066356",
            "count": 0
        },
        {
            "id": "100078845103003",
            "count": 0
        },
        {
            "id": "100079285240166",
            "count": 0
        },
        {
            "id": "100079513270995",
            "count": 0
        },
        {
            "id": "100079963475405",
            "count": 0
        },
        {
            "id": "100080124520611",
            "count": 0
        },
        {
            "id": "100081226167981",
            "count": 0
        },
        {
            "id": "100082325868634",
            "count": 0
        },
        {
            "id": "100082807352729",
            "count": 0
        },
        {
            "id": "100083533347591",
            "count": 1
        },
        {
            "id": "100083640636253",
            "count": 0
        },
        {
            "id": "100083922466937",
            "count": 0
        },
        {
            "id": "100084538040363",
            "count": 0
        },
        {
            "id": "100084623659132",
            "count": 0
        },
        {
            "id": "100084698671686",
            "count": 0
        },
        {
            "id": "100085090299768",
            "count": 0
        },
        {
            "id": "100085144508955",
            "count": 0
        },
        {
            "id": "100086904591784",
            "count": 0
        },
        {
            "id": "100087618891297",
            "count": 0
        },
        {
            "id": "100087901090721",
            "count": 0
        },
        {
            "id": "100088824086008",
            "count": 0
        },
        {
            "id": "100088864759028",
            "count": 0
        },
        {
            "id": "100089109107753",
            "count": 0
        },
        {
            "id": "100089438476334",
            "count": 0
        },
        {
            "id": "100090048876129",
            "count": 0
        },
        {
            "id": "100090081588719",
            "count": 0
        },
        {
            "id": "100090197495871",
            "count": 0
        },
        {
            "id": "100090664676287",
            "count": 0
        },
        {
            "id": "100091949653913",
            "count": 0
        },
        {
            "id": "100092552403184",
            "count": 0
        },
        {
            "id": "100093133314279",
            "count": 0
        },
        {
            "id": "100094252582107",
            "count": 0
        },
        {
            "id": "100094517442918",
            "count": 0
        },
        {
            "id": "100094639931547",
            "count": 0
        },
        {
            "id": "100095155576299",
            "count": 0
        },
        {
            "id": "100095256935627",
            "count": 0
        },
        {
            "id": "100095397944127",
            "count": 0
        },
        {
            "id": "100095539413563",
            "count": 0
        }
    ],
    "week": [
        {
            "id": "1197123062",
            "count": 0,
            "name": "Người dùng facebook"
        },
        {
            "id": "61550031276478",
            "count": 0,
            "name": "Người dùng facebook"
        },
        {
            "id": "61550107253260",
            "count": 0,
            "name": "Người dùng facebook"
        },
        {
            "id": "61550613790223",
            "count": 0,
            "name": "Người dùng facebook"
        },
        {
            "id": "61550756554683",
            "count": 0,
            "name": "Người dùng facebook"
        },
        {
            "id": "61550816582998",
            "count": 0,
            "name": "Người dùng facebook"
        },
        {
            "id": "61550960244237",
            "count": 0,
            "name": "Người dùng facebook"
        },
        {
            "id": "61552945585289",
            "count": 0,
            "name": "Người dùng facebook"
        },
        {
            "id": "61553659281345",
            "count": 0,
            "name": "Người dùng facebook"
        },
        {
            "id": "61554417387970",
            "count": 0,
            "name": "Người dùng facebook"
        },
        {
            "id": "61554433296893",
            "count": 0,
            "name": "Người dùng facebook"
        },
        {
            "id": "61555272445621",
            "count": 0,
            "name": "Người dùng facebook"
        },
        {
            "id": "61555511198283",
            "count": 0,
            "name": "Người dùng facebook"
        },
        {
            "id": "61555650861816",
            "count": 0,
            "name": "Người dùng facebook"
        },
        {
            "id": "61556026537354",
            "count": 0,
            "name": "Người dùng facebook"
        },
        {
            "id": "61556137711909",
            "count": 0,
            "name": "Người dùng facebook"
        },
        {
            "id": "61556199785981",
            "count": 0,
            "name": "Người dùng facebook"
        },
        {
            "id": "61556430681607",
            "count": 0,
            "name": "Người dùng facebook"
        },
        {
            "id": "100001483504823",
            "count": 0,
            "name": "Người dùng facebook"
        },
        {
            "id": "100005137653837",
            "count": 0,
            "name": "Người dùng facebook"
        },
        {
            "id": "100006551203604",
            "count": 0,
            "name": "Người dùng facebook"
        },
        {
            "id": "100010890945250",
            "count": 0,
            "name": "Người dùng facebook"
        },
        {
            "id": "100013375203759",
            "count": 0,
            "name": "Nguyễn Minh Tâm"
        },
        {
            "id": "100016477056398",
            "count": 0,
            "name": "Người dùng facebook"
        },
        {
            "id": "100021066455709",
            "count": 0,
            "name": "Người dùng facebook"
        },
        {
            "id": "100022709412936",
            "count": 0,
            "name": "Người dùng facebook"
        },
        {
            "id": "100022806620524",
            "count": 0,
            "name": "Người dùng facebook"
        },
        {
            "id": "100023250277879",
            "count": 0,
            "name": "Người dùng Facebook"
        },
        {
            "id": "100026359569628",
            "count": 0,
            "name": "Người dùng facebook"
        },
        {
            "id": "100026981884907",
            "count": 0,
            "name": "Người dùng facebook"
        },
        {
            "id": "100027244842325",
            "count": 0,
            "name": "Người dùng facebook"
        },
        {
            "id": "100028012126633",
            "count": 0,
            "name": "Người dùng facebook"
        },
        {
            "id": "100029905974007",
            "count": 0,
            "name": "Người dùng facebook"
        },
        {
            "id": "100030166266762",
            "count": 0,
            "name": "Người dùng facebook"
        },
        {
            "id": "100030258973537",
            "count": 0,
            "name": "Người dùng facebook"
        },
        {
            "id": "100033434828918",
            "count": 0,
            "name": "Người dùng facebook"
        },
        {
            "id": "100037833782670",
            "count": 0,
            "name": "Người dùng facebook"
        },
        {
            "id": "100037905271955",
            "count": 0,
            "name": "Người dùng facebook"
        },
        {
            "id": "100038664707166",
            "count": 0,
            "name": "Người dùng facebook"
        },
        {
            "id": "100041026933257",
            "count": 0,
            "name": "Người dùng facebook"
        },
        {
            "id": "100042077481734",
            "count": 0,
            "name": "Người dùng facebook"
        },
        {
            "id": "100045955503373",
            "count": 0,
            "name": "Người dùng facebook"
        },
        {
            "id": "100046099540344",
            "count": 0,
            "name": "Người dùng facebook"
        },
        {
            "id": "100048444757243",
            "count": 0,
            "name": "Người dùng facebook"
        },
        {
            "id": "100050038279181",
            "count": 0,
            "name": "Người dùng facebook"
        },
        {
            "id": "100050224210035",
            "count": 0,
            "name": "Người dùng facebook"
        },
        {
            "id": "100051870045481",
            "count": 0,
            "name": "Người dùng facebook"
        },
        {
            "id": "100052333065163",
            "count": 0,
            "name": "Người dùng facebook"
        },
        {
            "id": "100053586144323",
            "count": 0,
            "name": "Người dùng facebook"
        },
        {
            "id": "100054496869415",
            "count": 0,
            "name": "Người dùng facebook"
        },
        {
            "id": "100054868245935",
            "count": 0,
            "name": "Người dùng facebook"
        },
        {
            "id": "100054870732307",
            "count": 0,
            "name": "Người dùng facebook"
        },
        {
            "id": "100056426214479",
            "count": 0,
            "name": "Người dùng facebook"
        },
        {
            "id": "100056702887203",
            "count": 0,
            "name": "Người dùng facebook"
        },
        {
            "id": "100056745708577",
            "count": 0,
            "name": "Người dùng facebook"
        },
        {
            "id": "100058606900376",
            "count": 0,
            "name": "Người dùng facebook"
        },
        {
            "id": "100058970956271",
            "count": 0,
            "name": "Người dùng facebook"
        },
        {
            "id": "100059906962202",
            "count": 0,
            "name": "Người dùng facebook"
        },
        {
            "id": "100060035434807",
            "count": 0,
            "name": "Người dùng facebook"
        },
        {
            "id": "100060779195213",
            "count": 0,
            "name": "Người dùng facebook"
        },
        {
            "id": "100060923303072",
            "count": 0,
            "name": "Người dùng facebook"
        },
        {
            "id": "100061212372279",
            "count": 0,
            "name": "Người dùng facebook"
        },
        {
            "id": "100061638674575",
            "count": 0,
            "name": "Người dùng facebook"
        },
        {
            "id": "100061681069898",
            "count": 0,
            "name": "Minh Tâm"
        },
        {
            "id": "100062591730134",
            "count": 0,
            "name": "Người dùng facebook"
        },
        {
            "id": "100063600891672",
            "count": 0,
            "name": "Người dùng facebook"
        },
        {
            "id": "100063773742944",
            "count": 0,
            "name": "Người dùng facebook"
        },
        {
            "id": "100065116733444",
            "count": 0,
            "name": "Người dùng facebook"
        },
        {
            "id": "100065302164449",
            "count": 0,
            "name": "Người dùng facebook"
        },
        {
            "id": "100066073701917",
            "count": 0,
            "name": "Người dùng facebook"
        },
        {
            "id": "100066228437034",
            "count": 0,
            "name": "Người dùng facebook"
        },
        {
            "id": "100067377774776",
            "count": 0,
            "name": "Người dùng facebook"
        },
        {
            "id": "100067463912717",
            "count": 0,
            "name": "Người dùng facebook"
        },
        {
            "id": "100069877930512",
            "count": 0,
            "name": "Người dùng facebook"
        },
        {
            "id": "100072122673872",
            "count": 0,
            "name": "Người dùng facebook"
        },
        {
            "id": "100072603382299",
            "count": 0,
            "name": "Người dùng facebook"
        },
        {
            "id": "100072994342483",
            "count": 0,
            "name": "Người dùng facebook"
        },
        {
            "id": "100073119091740",
            "count": 0,
            "name": "Người dùng facebook"
        },
        {
            "id": "100073603485750",
            "count": 0,
            "name": "Người dùng facebook"
        },
        {
            "id": "100073655200260",
            "count": 0,
            "name": "Người dùng facebook"
        },
        {
            "id": "100073786282614",
            "count": 0,
            "name": "Người dùng facebook"
        },
        {
            "id": "100074331896453",
            "count": 0,
            "name": "Người dùng facebook"
        },
        {
            "id": "100074720064406",
            "count": 0,
            "name": "Người dùng facebook"
        },
        {
            "id": "100075398285629",
            "count": 0,
            "name": "Người dùng facebook"
        },
        {
            "id": "100075401613274",
            "count": 0,
            "name": "Người dùng facebook"
        },
        {
            "id": "100075509484911",
            "count": 0,
            "name": "Người dùng facebook"
        },
        {
            "id": "100076240372790",
            "count": 0,
            "name": "Người dùng facebook"
        },
        {
            "id": "100076614848111",
            "count": 0,
            "name": "Người dùng facebook"
        },
        {
            "id": "100077099160173",
            "count": 0,
            "name": "Người dùng facebook"
        },
        {
            "id": "100077129421074",
            "count": 0,
            "name": "Người dùng facebook"
        },
        {
            "id": "100077532079160",
            "count": 0,
            "name": "Người dùng facebook"
        },
        {
            "id": "100077725557978",
            "count": 0,
            "name": "Người dùng facebook"
        },
        {
            "id": "100078187066356",
            "count": 0,
            "name": "Người dùng facebook"
        },
        {
            "id": "100078845103003",
            "count": 0,
            "name": "Người dùng facebook"
        },
        {
            "id": "100079285240166",
            "count": 0,
            "name": "Người dùng facebook"
        },
        {
            "id": "100079513270995",
            "count": 0,
            "name": "Người dùng facebook"
        },
        {
            "id": "100079963475405",
            "count": 0,
            "name": "Người dùng facebook"
        },
        {
            "id": "100080124520611",
            "count": 0,
            "name": "Người dùng facebook"
        },
        {
            "id": "100081226167981",
            "count": 0,
            "name": "Người dùng facebook"
        },
        {
            "id": "100082325868634",
            "count": 0,
            "name": "Người dùng facebook"
        },
        {
            "id": "100082807352729",
            "count": 0,
            "name": "Người dùng facebook"
        },
        {
            "id": "100083533347591",
            "count": 0,
            "name": "Người dùng facebook"
        },
        {
            "id": "100083640636253",
            "count": 0,
            "name": "Người dùng facebook"
        },
        {
            "id": "100083922466937",
            "count": 0,
            "name": "Người dùng facebook"
        },
        {
            "id": "100084538040363",
            "count": 0,
            "name": "Người dùng facebook"
        },
        {
            "id": "100084623659132",
            "count": 0,
            "name": "Người dùng facebook"
        },
        {
            "id": "100084698671686",
            "count": 0,
            "name": "Người dùng facebook"
        },
        {
            "id": "100085090299768",
            "count": 0,
            "name": "Người dùng facebook"
        },
        {
            "id": "100085144508955",
            "count": 0,
            "name": "Người dùng facebook"
        },
        {
            "id": "100086904591784",
            "count": 0,
            "name": "Người dùng facebook"
        },
        {
            "id": "100087618891297",
            "count": 0,
            "name": "Người dùng facebook"
        },
        {
            "id": "100087901090721",
            "count": 0,
            "name": "Người dùng facebook"
        },
        {
            "id": "100088824086008",
            "count": 0,
            "name": "Người dùng facebook"
        },
        {
            "id": "100088864759028",
            "count": 0,
            "name": "Người dùng facebook"
        },
        {
            "id": "100089109107753",
            "count": 0,
            "name": "Người dùng facebook"
        },
        {
            "id": "100089438476334",
            "count": 0,
            "name": "Người dùng facebook"
        },
        {
            "id": "100090048876129",
            "count": 0,
            "name": "Người dùng facebook"
        },
        {
            "id": "100090081588719",
            "count": 0,
            "name": "Người dùng facebook"
        },
        {
            "id": "100090197495871",
            "count": 0,
            "name": "Người dùng facebook"
        },
        {
            "id": "100090664676287",
            "count": 0,
            "name": "Trọng Trung"
        },
        {
            "id": "100091949653913",
            "count": 0,
            "name": "Người dùng facebook"
        },
        {
            "id": "100092552403184",
            "count": 0,
            "name": "Người dùng facebook"
        },
        {
            "id": "100093133314279",
            "count": 0,
            "name": "Người dùng facebook"
        },
        {
            "id": "100094252582107",
            "count": 0,
            "name": "Người dùng facebook"
        },
        {
            "id": "100094517442918",
            "count": 0,
            "name": "Người dùng facebook"
        },
        {
            "id": "100094639931547",
            "count": 0,
            "name": "Người dùng facebook"
        },
        {
            "id": "100095155576299",
            "count": 0,
            "name": "Người dùng facebook"
        },
        {
            "id": "100095256935627",
            "count": 0,
            "name": "Người dùng facebook"
        },
        {
            "id": "100095397944127",
            "count": 0,
            "name": "Người dùng facebook"
        },
        {
            "id": "100095539413563",
            "count": 0,
            "name": "Người dùng facebook"
        }
    ],
    "day": [
        {
            "id": "1197123062",
            "count": 0,
            "name": "Người dùng facebook"
        },
        {
            "id": "61550031276478",
            "count": 0,
            "name": "Người dùng facebook"
        },
        {
            "id": "61550107253260",
            "count": 0,
            "name": "Người dùng facebook"
        },
        {
            "id": "61550613790223",
            "count": 0,
            "name": "Người dùng facebook"
        },
        {
            "id": "61550756554683",
            "count": 0,
            "name": "Người dùng facebook"
        },
        {
            "id": "61550816582998",
            "count": 0,
            "name": "Người dùng facebook"
        },
        {
            "id": "61550960244237",
            "count": 0,
            "name": "Người dùng facebook"
        },
        {
            "id": "61552945585289",
            "count": 0,
            "name": "Người dùng facebook"
        },
        {
            "id": "61553659281345",
            "count": 0,
            "name": "Người dùng facebook"
        },
        {
            "id": "61554417387970",
            "count": 0,
            "name": "Người dùng facebook"
        },
        {
            "id": "61554433296893",
            "count": 0,
            "name": "Người dùng facebook"
        },
        {
            "id": "61555272445621",
            "count": 0,
            "name": "Người dùng facebook"
        },
        {
            "id": "61555511198283",
            "count": 0,
            "name": "Người dùng facebook"
        },
        {
            "id": "61555650861816",
            "count": 0,
            "name": "Người dùng facebook"
        },
        {
            "id": "61556026537354",
            "count": 0,
            "name": "Người dùng facebook"
        },
        {
            "id": "61556137711909",
            "count": 0,
            "name": "Người dùng facebook"
        },
        {
            "id": "61556199785981",
            "count": 0,
            "name": "Người dùng facebook"
        },
        {
            "id": "61556430681607",
            "count": 0,
            "name": "Người dùng facebook"
        },
        {
            "id": "100001483504823",
            "count": 0,
            "name": "Người dùng facebook"
        },
        {
            "id": "100005137653837",
            "count": 0,
            "name": "Người dùng facebook"
        },
        {
            "id": "100006551203604",
            "count": 0,
            "name": "Người dùng facebook"
        },
        {
            "id": "100010890945250",
            "count": 0,
            "name": "Người dùng facebook"
        },
        {
            "id": "100013375203759",
            "count": 0,
            "name": "Nguyễn Minh Tâm"
        },
        {
            "id": "100016477056398",
            "count": 0,
            "name": "Người dùng facebook"
        },
        {
            "id": "100021066455709",
            "count": 0,
            "name": "Người dùng facebook"
        },
        {
            "id": "100022709412936",
            "count": 0,
            "name": "Người dùng facebook"
        },
        {
            "id": "100022806620524",
            "count": 0,
            "name": "Người dùng facebook"
        },
        {
            "id": "100023250277879",
            "count": 0,
            "name": "Người dùng Facebook"
        },
        {
            "id": "100026359569628",
            "count": 0,
            "name": "Người dùng facebook"
        },
        {
            "id": "100026981884907",
            "count": 0,
            "name": "Người dùng facebook"
        },
        {
            "id": "100027244842325",
            "count": 0,
            "name": "Người dùng facebook"
        },
        {
            "id": "100028012126633",
            "count": 0,
            "name": "Người dùng facebook"
        },
        {
            "id": "100029905974007",
            "count": 0,
            "name": "Người dùng facebook"
        },
        {
            "id": "100030166266762",
            "count": 0,
            "name": "Người dùng facebook"
        },
        {
            "id": "100030258973537",
            "count": 0,
            "name": "Người dùng facebook"
        },
        {
            "id": "100033434828918",
            "count": 0,
            "name": "Người dùng facebook"
        },
        {
            "id": "100037833782670",
            "count": 0,
            "name": "Người dùng facebook"
        },
        {
            "id": "100037905271955",
            "count": 0,
            "name": "Người dùng facebook"
        },
        {
            "id": "100038664707166",
            "count": 0,
            "name": "Người dùng facebook"
        },
        {
            "id": "100041026933257",
            "count": 0,
            "name": "Người dùng facebook"
        },
        {
            "id": "100042077481734",
            "count": 0,
            "name": "Người dùng facebook"
        },
        {
            "id": "100045955503373",
            "count": 0,
            "name": "Người dùng facebook"
        },
        {
            "id": "100046099540344",
            "count": 0,
            "name": "Người dùng facebook"
        },
        {
            "id": "100048444757243",
            "count": 0,
            "name": "Người dùng facebook"
        },
        {
            "id": "100050038279181",
            "count": 0,
            "name": "Người dùng facebook"
        },
        {
            "id": "100050224210035",
            "count": 0,
            "name": "Người dùng facebook"
        },
        {
            "id": "100051870045481",
            "count": 0,
            "name": "Người dùng facebook"
        },
        {
            "id": "100052333065163",
            "count": 0,
            "name": "Người dùng facebook"
        },
        {
            "id": "100053586144323",
            "count": 0,
            "name": "Người dùng facebook"
        },
        {
            "id": "100054496869415",
            "count": 0,
            "name": "Người dùng facebook"
        },
        {
            "id": "100054868245935",
            "count": 0,
            "name": "Người dùng facebook"
        },
        {
            "id": "100054870732307",
            "count": 0,
            "name": "Người dùng facebook"
        },
        {
            "id": "100056426214479",
            "count": 0,
            "name": "Người dùng facebook"
        },
        {
            "id": "100056702887203",
            "count": 0,
            "name": "Người dùng facebook"
        },
        {
            "id": "100056745708577",
            "count": 0,
            "name": "Người dùng facebook"
        },
        {
            "id": "100058606900376",
            "count": 0,
            "name": "Người dùng facebook"
        },
        {
            "id": "100058970956271",
            "count": 0,
            "name": "Người dùng facebook"
        },
        {
            "id": "100059906962202",
            "count": 0,
            "name": "Người dùng facebook"
        },
        {
            "id": "100060035434807",
            "count": 0,
            "name": "Người dùng facebook"
        },
        {
            "id": "100060779195213",
            "count": 0,
            "name": "Người dùng facebook"
        },
        {
            "id": "100060923303072",
            "count": 0,
            "name": "Người dùng facebook"
        },
        {
            "id": "100061212372279",
            "count": 0,
            "name": "Người dùng facebook"
        },
        {
            "id": "100061638674575",
            "count": 0,
            "name": "Người dùng facebook"
        },
        {
            "id": "100061681069898",
            "count": 0,
            "name": "Minh Tâm"
        },
        {
            "id": "100062591730134",
            "count": 0,
            "name": "Người dùng facebook"
        },
        {
            "id": "100063600891672",
            "count": 0,
            "name": "Người dùng facebook"
        },
        {
            "id": "100063773742944",
            "count": 0,
            "name": "Người dùng facebook"
        },
        {
            "id": "100065116733444",
            "count": 0,
            "name": "Người dùng facebook"
        },
        {
            "id": "100065302164449",
            "count": 0,
            "name": "Người dùng facebook"
        },
        {
            "id": "100066073701917",
            "count": 0,
            "name": "Người dùng facebook"
        },
        {
            "id": "100066228437034",
            "count": 0,
            "name": "Người dùng facebook"
        },
        {
            "id": "100067377774776",
            "count": 0,
            "name": "Người dùng facebook"
        },
        {
            "id": "100067463912717",
            "count": 0,
            "name": "Người dùng facebook"
        },
        {
            "id": "100069877930512",
            "count": 0,
            "name": "Người dùng facebook"
        },
        {
            "id": "100072122673872",
            "count": 0,
            "name": "Người dùng facebook"
        },
        {
            "id": "100072603382299",
            "count": 0,
            "name": "Người dùng facebook"
        },
        {
            "id": "100072994342483",
            "count": 0,
            "name": "Người dùng facebook"
        },
        {
            "id": "100073119091740",
            "count": 0,
            "name": "Người dùng facebook"
        },
        {
            "id": "100073603485750",
            "count": 0,
            "name": "Người dùng facebook"
        },
        {
            "id": "100073655200260",
            "count": 0,
            "name": "Người dùng facebook"
        },
        {
            "id": "100073786282614",
            "count": 0,
            "name": "Người dùng facebook"
        },
        {
            "id": "100074331896453",
            "count": 0,
            "name": "Người dùng facebook"
        },
        {
            "id": "100074720064406",
            "count": 0,
            "name": "Người dùng facebook"
        },
        {
            "id": "100075398285629",
            "count": 0,
            "name": "Người dùng facebook"
        },
        {
            "id": "100075401613274",
            "count": 0,
            "name": "Người dùng facebook"
        },
        {
            "id": "100075509484911",
            "count": 0,
            "name": "Người dùng facebook"
        },
        {
            "id": "100076240372790",
            "count": 0,
            "name": "Người dùng facebook"
        },
        {
            "id": "100076614848111",
            "count": 0,
            "name": "Người dùng facebook"
        },
        {
            "id": "100077099160173",
            "count": 0,
            "name": "Người dùng facebook"
        },
        {
            "id": "100077129421074",
            "count": 0,
            "name": "Người dùng facebook"
        },
        {
            "id": "100077532079160",
            "count": 0,
            "name": "Người dùng facebook"
        },
        {
            "id": "100077725557978",
            "count": 0,
            "name": "Người dùng facebook"
        },
        {
            "id": "100078187066356",
            "count": 0,
            "name": "Người dùng facebook"
        },
        {
            "id": "100078845103003",
            "count": 0,
            "name": "Người dùng facebook"
        },
        {
            "id": "100079285240166",
            "count": 0,
            "name": "Người dùng facebook"
        },
        {
            "id": "100079513270995",
            "count": 0,
            "name": "Người dùng facebook"
        },
        {
            "id": "100079963475405",
            "count": 0,
            "name": "Người dùng facebook"
        },
        {
            "id": "100080124520611",
            "count": 0,
            "name": "Người dùng facebook"
        },
        {
            "id": "100081226167981",
            "count": 0,
            "name": "Người dùng facebook"
        },
        {
            "id": "100082325868634",
            "count": 0,
            "name": "Người dùng facebook"
        },
        {
            "id": "100082807352729",
            "count": 0,
            "name": "Người dùng facebook"
        },
        {
            "id": "100083533347591",
            "count": 0,
            "name": "Người dùng facebook"
        },
        {
            "id": "100083640636253",
            "count": 0,
            "name": "Người dùng facebook"
        },
        {
            "id": "100083922466937",
            "count": 0,
            "name": "Người dùng facebook"
        },
        {
            "id": "100084538040363",
            "count": 0,
            "name": "Người dùng facebook"
        },
        {
            "id": "100084623659132",
            "count": 0,
            "name": "Người dùng facebook"
        },
        {
            "id": "100084698671686",
            "count": 0,
            "name": "Người dùng facebook"
        },
        {
            "id": "100085090299768",
            "count": 0,
            "name": "Người dùng facebook"
        },
        {
            "id": "100085144508955",
            "count": 0,
            "name": "Người dùng facebook"
        },
        {
            "id": "100086904591784",
            "count": 0,
            "name": "Người dùng facebook"
        },
        {
            "id": "100087618891297",
            "count": 0,
            "name": "Người dùng facebook"
        },
        {
            "id": "100087901090721",
            "count": 0,
            "name": "Người dùng facebook"
        },
        {
            "id": "100088824086008",
            "count": 0,
            "name": "Người dùng facebook"
        },
        {
            "id": "100088864759028",
            "count": 0,
            "name": "Người dùng facebook"
        },
        {
            "id": "100089109107753",
            "count": 0,
            "name": "Người dùng facebook"
        },
        {
            "id": "100089438476334",
            "count": 0,
            "name": "Người dùng facebook"
        },
        {
            "id": "100090048876129",
            "count": 0,
            "name": "Người dùng facebook"
        },
        {
            "id": "100090081588719",
            "count": 0,
            "name": "Người dùng facebook"
        },
        {
            "id": "100090197495871",
            "count": 0,
            "name": "Người dùng facebook"
        },
        {
            "id": "100090664676287",
            "count": 0,
            "name": "Trọng Trung"
        },
        {
            "id": "100091949653913",
            "count": 0,
            "name": "Người dùng facebook"
        },
        {
            "id": "100092552403184",
            "count": 0,
            "name": "Người dùng facebook"
        },
        {
            "id": "100093133314279",
            "count": 0,
            "name": "Người dùng facebook"
        },
        {
            "id": "100094252582107",
            "count": 0,
            "name": "Người dùng facebook"
        },
        {
            "id": "100094517442918",
            "count": 0,
            "name": "Người dùng facebook"
        },
        {
            "id": "100094639931547",
            "count": 0,
            "name": "Người dùng facebook"
        },
        {
            "id": "100095155576299",
            "count": 0,
            "name": "Người dùng facebook"
        },
        {
            "id": "100095256935627",
            "count": 0,
            "name": "Người dùng facebook"
        },
        {
            "id": "100095397944127",
            "count": 0,
            "name": "Người dùng facebook"
        },
        {
            "id": "100095539413563",
            "count": 0,
            "name": "Người dùng facebook"
        }
    ],
    "time": 3
}