{
    "total": [
        {
            "id": "100009288627141",
            "count": 0
        },
        {
            "id": "100013074420199",
            "count": 0
        },
        {
            "id": "100023250277879",
            "count": 5
        },
        {
            "id": "100025340854489",
            "count": 0
        },
        {
            "id": "100025976982919",
            "count": 0
        },
        {
            "id": "100040922983131",
            "count": 0
        },
        {
            "id": "100041054234903",
            "count": 0
        },
        {
            "id": "100046262590054",
            "count": 0
        },
        {
            "id": "100046618612572",
            "count": 3
        },
        {
            "id": "100048452412222",
            "count": 0
        },
        {
            "id": "100048479196349",
            "count": 0
        },
        {
            "id": "100049664452631",
            "count": 76
        },
        {
            "id": "100049719559171",
            "count": 145
        },
        {
            "id": "100049735254389",
            "count": 5
        },
        {
            "id": "100049944961348",
            "count": 0
        },
        {
            "id": "100050203730446",
            "count": 19
        },
        {
            "id": "100051500760682",
            "count": 0
        },
        {
            "id": "100052484168838",
            "count": 0
        },
        {
            "id": "100053658735072",
            "count": 0
        },
        {
            "id": "100054387824870",
            "count": 1
        },
        {
            "id": "100055445830854",
            "count": 0
        },
        {
            "id": "100056063895388",
            "count": 0
        },
        {
            "id": "100056905673878",
            "count": 0
        },
        {
            "id": "100056908487439",
            "count": 0
        },
        {
            "id": "100057346640782",
            "count": 0
        },
        {
            "id": "100057469185744",
            "count": 0
        },
        {
            "id": "100058017127468",
            "count": 0
        },
        {
            "id": "100059293400126",
            "count": 135
        },
        {
            "id": "100059435633751",
            "count": 170
        },
        {
            "id": "100059650972916",
            "count": 1
        },
        {
            "id": "100059921825788",
            "count": 0
        },
        {
            "id": "100060160005306",
            "count": 0
        },
        {
            "id": "100060736756146",
            "count": 8
        },
        {
            "id": "100063144067332",
            "count": 0
        },
        {
            "id": "100063368597214",
            "count": 0
        },
        {
            "id": "100063530955135",
            "count": 0
        },
        {
            "id": "100063531206707",
            "count": 0
        },
        {
            "id": "100065106760629",
            "count": 25
        },
        {
            "id": "100066350868887",
            "count": 0
        },
        {
            "id": "100067327646975",
            "count": 0
        },
        {
            "id": "100067527685328",
            "count": 0
        },
        {
            "id": "100068259756683",
            "count": 0
        },
        {
            "id": "100069462471621",
            "count": 0
        },
        {
            "id": "100070217311047",
            "count": 0
        },
        {
            "id": "100070639362261",
            "count": 0
        },
        {
            "id": "100070889514699",
            "count": 0
        },
        {
            "id": "100070918685312",
            "count": 0
        },
        {
            "id": "100070993077260",
            "count": 0
        },
        {
            "id": "100071676530177",
            "count": 74
        },
        {
            "id": "100071878207269",
            "count": 0
        },
        {
            "id": "100072376201236",
            "count": 0
        },
        {
            "id": "100072476622464",
            "count": 0
        },
        {
            "id": "100072675626566",
            "count": 1
        },
        {
            "id": "100072736390649",
            "count": 7
        },
        {
            "id": "100072986970167",
            "count": 0
        },
        {
            "id": "100073308109648",
            "count": 0
        },
        {
            "id": "100073384754552",
            "count": 236
        },
        {
            "id": "100073458698273",
            "count": 0
        },
        {
            "id": "100073519582661",
            "count": 0
        },
        {
            "id": "100073681931859",
            "count": 0
        },
        {
            "id": "100074730408833",
            "count": 0
        },
        {
            "id": "100074731273232",
            "count": 0
        },
        {
            "id": "100074874152789",
            "count": 0
        },
        {
            "id": "100075049867323",
            "count": 10
        },
        {
            "id": "100075084227860",
            "count": 0
        },
        {
            "id": "100075146145340",
            "count": 0
        },
        {
            "id": "100075181744544",
            "count": 0
        },
        {
            "id": "100076926289765",
            "count": 0
        },
        {
            "id": "100077911120935",
            "count": 0
        },
        {
            "id": "100078312846000",
            "count": 0
        },
        {
            "id": "100078539427115",
            "count": 0
        },
        {
            "id": "100078562897868",
            "count": 4
        },
        {
            "id": "100078714319232",
            "count": 0
        },
        {
            "id": "100079138365262",
            "count": 0
        },
        {
            "id": "100079225460443",
            "count": 0
        },
        {
            "id": "100079264843097",
            "count": 0
        },
        {
            "id": "100079894541249",
            "count": 0
        },
        {
            "id": "100080066552735",
            "count": 0
        },
        {
            "id": "100080145905071",
            "count": 0
        },
        {
            "id": "100080229300189",
            "count": 0
        },
        {
            "id": "100080251070141",
            "count": 0
        },
        {
            "id": "100081168608728",
            "count": 27
        },
        {
            "id": "100081347157671",
            "count": 4
        },
        {
            "id": "100081540274688",
            "count": 79
        },
        {
            "id": "100082289148128",
            "count": 0
        },
        {
            "id": "100082754524557",
            "count": 0
        },
        {
            "id": "100083206190313",
            "count": 21
        },
        {
            "id": "100083708986199",
            "count": 5
        },
        {
            "id": "100083786662840",
            "count": 0
        },
        {
            "id": "100084136490078",
            "count": 0
        },
        {
            "id": "100084277832142",
            "count": 0
        },
        {
            "id": "100084509209404",
            "count": 0
        },
        {
            "id": "100084516589945",
            "count": 0
        },
        {
            "id": "100084735526565",
            "count": 0
        },
        {
            "id": "100084736032258",
            "count": 1
        },
        {
            "id": "100084852637978",
            "count": 0
        },
        {
            "id": "100084980013051",
            "count": 0
        },
        {
            "id": "100085624261769",
            "count": 0
        },
        {
            "id": "100086280722638",
            "count": 0
        },
        {
            "id": "100086293245287",
            "count": 0
        },
        {
            "id": "100086985161146",
            "count": 0
        },
        {
            "id": "100087499030458",
            "count": 34
        },
        {
            "id": "100087627632878",
            "count": 0
        },
        {
            "id": "100087645395449",
            "count": 0
        },
        {
            "id": "100087941115166",
            "count": 0
        },
        {
            "id": "100088741953052",
            "count": 0
        },
        {
            "id": "100088873552113",
            "count": 0
        },
        {
            "id": "100088947065380",
            "count": 0
        },
        {
            "id": "100089336877077",
            "count": 0
        },
        {
            "id": "100089438408044",
            "count": 0
        },
        {
            "id": "100089974189493",
            "count": 0
        },
        {
            "id": "100090648552155",
            "count": 0
        },
        {
            "id": "100092614584832",
            "count": 0
        },
        {
            "id": "100094073404198",
            "count": 0
        },
        {
            "id": "100094104075713",
            "count": 1
        },
        {
            "id": "100094412376863",
            "count": 60
        }
    ],
    "week": [
        {
            "id": "100009288627141",
            "count": 0,
            "name": "Người dùng facebook"
        },
        {
            "id": "100013074420199",
            "count": 0,
            "name": "Người dùng facebook"
        },
        {
            "id": "100023250277879",
            "count": 0,
            "name": "Người dùng Facebook"
        },
        {
            "id": "100025340854489",
            "count": 0,
            "name": "Người dùng facebook"
        },
        {
            "id": "100025976982919",
            "count": 0,
            "name": "Người dùng facebook"
        },
        {
            "id": "100040922983131",
            "count": 0,
            "name": "Người dùng facebook"
        },
        {
            "id": "100041054234903",
            "count": 0,
            "name": "Người dùng facebook"
        },
        {
            "id": "100046262590054",
            "count": 0,
            "name": "Người dùng facebook"
        },
        {
            "id": "100046618612572",
            "count": 0,
            "name": "Người dùng facebook"
        },
        {
            "id": "100048452412222",
            "count": 0,
            "name": "Người dùng facebook"
        },
        {
            "id": "100048479196349",
            "count": 0,
            "name": "Người dùng facebook"
        },
        {
            "id": "100049664452631",
            "count": 0,
            "name": "Người dùng facebook"
        },
        {
            "id": "100049719559171",
            "count": 0,
            "name": "Người dùng facebook"
        },
        {
            "id": "100049735254389",
            "count": 0,
            "name": "Người dùng facebook"
        },
        {
            "id": "100049944961348",
            "count": 0,
            "name": "Người dùng facebook"
        },
        {
            "id": "100050203730446",
            "count": 0,
            "name": "Người dùng facebook"
        },
        {
            "id": "100051500760682",
            "count": 0,
            "name": "Người dùng facebook"
        },
        {
            "id": "100052484168838",
            "count": 0,
            "name": "Người dùng facebook"
        },
        {
            "id": "100053658735072",
            "count": 0,
            "name": "Người dùng facebook"
        },
        {
            "id": "100054387824870",
            "count": 0,
            "name": "Người dùng facebook"
        },
        {
            "id": "100055445830854",
            "count": 0,
            "name": "Người dùng facebook"
        },
        {
            "id": "100056063895388",
            "count": 0,
            "name": "Người dùng facebook"
        },
        {
            "id": "100056905673878",
            "count": 0,
            "name": "Người dùng facebook"
        },
        {
            "id": "100056908487439",
            "count": 0,
            "name": "Người dùng facebook"
        },
        {
            "id": "100057346640782",
            "count": 0,
            "name": "Người dùng facebook"
        },
        {
            "id": "100057469185744",
            "count": 0,
            "name": "Người dùng facebook"
        },
        {
            "id": "100058017127468",
            "count": 0,
            "name": "Người dùng facebook"
        },
        {
            "id": "100059293400126",
            "count": 0,
            "name": "Người dùng facebook"
        },
        {
            "id": "100059435633751",
            "count": 0,
            "name": "Người dùng facebook"
        },
        {
            "id": "100059650972916",
            "count": 0,
            "name": "Người dùng facebook"
        },
        {
            "id": "100059921825788",
            "count": 0,
            "name": "Người dùng facebook"
        },
        {
            "id": "100060160005306",
            "count": 0,
            "name": "Người dùng facebook"
        },
        {
            "id": "100060736756146",
            "count": 0,
            "name": "Người dùng facebook"
        },
        {
            "id": "100063144067332",
            "count": 0,
            "name": "Người dùng facebook"
        },
        {
            "id": "100063368597214",
            "count": 0,
            "name": "Người dùng facebook"
        },
        {
            "id": "100063530955135",
            "count": 0,
            "name": "Người dùng facebook"
        },
        {
            "id": "100063531206707",
            "count": 0,
            "name": "Người dùng facebook"
        },
        {
            "id": "100065106760629",
            "count": 0,
            "name": "Người dùng facebook"
        },
        {
            "id": "100066350868887",
            "count": 0,
            "name": "Người dùng facebook"
        },
        {
            "id": "100067327646975",
            "count": 0,
            "name": "Người dùng facebook"
        },
        {
            "id": "100067527685328",
            "count": 0,
            "name": "Người dùng facebook"
        },
        {
            "id": "100068259756683",
            "count": 0,
            "name": "Người dùng facebook"
        },
        {
            "id": "100069462471621",
            "count": 0,
            "name": "Người dùng facebook"
        },
        {
            "id": "100070217311047",
            "count": 0,
            "name": "Người dùng facebook"
        },
        {
            "id": "100070639362261",
            "count": 0,
            "name": "Người dùng facebook"
        },
        {
            "id": "100070889514699",
            "count": 0,
            "name": "Người dùng facebook"
        },
        {
            "id": "100070918685312",
            "count": 0,
            "name": "Người dùng facebook"
        },
        {
            "id": "100070993077260",
            "count": 0,
            "name": "Người dùng facebook"
        },
        {
            "id": "100071676530177",
            "count": 0,
            "name": "Người dùng facebook"
        },
        {
            "id": "100071878207269",
            "count": 0,
            "name": "Người dùng facebook"
        },
        {
            "id": "100072376201236",
            "count": 0,
            "name": "Người dùng facebook"
        },
        {
            "id": "100072476622464",
            "count": 0,
            "name": "Người dùng facebook"
        },
        {
            "id": "100072675626566",
            "count": 0,
            "name": "Người dùng facebook"
        },
        {
            "id": "100072736390649",
            "count": 0,
            "name": "Người dùng facebook"
        },
        {
            "id": "100072986970167",
            "count": 0,
            "name": "Người dùng facebook"
        },
        {
            "id": "100073308109648",
            "count": 0,
            "name": "Người dùng facebook"
        },
        {
            "id": "100073384754552",
            "count": 0,
            "name": "Người dùng facebook"
        },
        {
            "id": "100073458698273",
            "count": 0,
            "name": "Người dùng facebook"
        },
        {
            "id": "100073519582661",
            "count": 0,
            "name": "Người dùng facebook"
        },
        {
            "id": "100073681931859",
            "count": 0,
            "name": "Người dùng facebook"
        },
        {
            "id": "100074730408833",
            "count": 0,
            "name": "Người dùng facebook"
        },
        {
            "id": "100074731273232",
            "count": 0,
            "name": "Người dùng facebook"
        },
        {
            "id": "100074874152789",
            "count": 0,
            "name": "Người dùng facebook"
        },
        {
            "id": "100075049867323",
            "count": 0,
            "name": "Người dùng facebook"
        },
        {
            "id": "100075084227860",
            "count": 0,
            "name": "Người dùng facebook"
        },
        {
            "id": "100075146145340",
            "count": 0,
            "name": "Người dùng facebook"
        },
        {
            "id": "100075181744544",
            "count": 0,
            "name": "Người dùng facebook"
        },
        {
            "id": "100076926289765",
            "count": 0,
            "name": "Người dùng facebook"
        },
        {
            "id": "100077911120935",
            "count": 0,
            "name": "Người dùng facebook"
        },
        {
            "id": "100078312846000",
            "count": 0,
            "name": "Người dùng facebook"
        },
        {
            "id": "100078539427115",
            "count": 0,
            "name": "Người dùng facebook"
        },
        {
            "id": "100078562897868",
            "count": 0,
            "name": "Người dùng facebook"
        },
        {
            "id": "100078714319232",
            "count": 0,
            "name": "Người dùng facebook"
        },
        {
            "id": "100079138365262",
            "count": 0,
            "name": "Người dùng facebook"
        },
        {
            "id": "100079225460443",
            "count": 0,
            "name": "Người dùng facebook"
        },
        {
            "id": "100079264843097",
            "count": 0,
            "name": "Người dùng facebook"
        },
        {
            "id": "100079894541249",
            "count": 0,
            "name": "Người dùng facebook"
        },
        {
            "id": "100080066552735",
            "count": 0,
            "name": "Người dùng facebook"
        },
        {
            "id": "100080145905071",
            "count": 0,
            "name": "Người dùng facebook"
        },
        {
            "id": "100080229300189",
            "count": 0,
            "name": "Người dùng facebook"
        },
        {
            "id": "100080251070141",
            "count": 0,
            "name": "Người dùng facebook"
        },
        {
            "id": "100081168608728",
            "count": 0,
            "name": "Người dùng facebook"
        },
        {
            "id": "100081347157671",
            "count": 0,
            "name": "Người dùng facebook"
        },
        {
            "id": "100081540274688",
            "count": 0,
            "name": "Người dùng facebook"
        },
        {
            "id": "100082289148128",
            "count": 0,
            "name": "Người dùng facebook"
        },
        {
            "id": "100082754524557",
            "count": 0,
            "name": "Người dùng facebook"
        },
        {
            "id": "100083206190313",
            "count": 0,
            "name": "Người dùng facebook"
        },
        {
            "id": "100083708986199",
            "count": 0,
            "name": "Người dùng facebook"
        },
        {
            "id": "100083786662840",
            "count": 0,
            "name": "Người dùng facebook"
        },
        {
            "id": "100084136490078",
            "count": 0,
            "name": "Người dùng facebook"
        },
        {
            "id": "100084277832142",
            "count": 0,
            "name": "Người dùng facebook"
        },
        {
            "id": "100084509209404",
            "count": 0,
            "name": "Người dùng facebook"
        },
        {
            "id": "100084516589945",
            "count": 0,
            "name": "Người dùng facebook"
        },
        {
            "id": "100084735526565",
            "count": 0,
            "name": "Đỗ Nv Một"
        },
        {
            "id": "100084736032258",
            "count": 0,
            "name": "Người dùng facebook"
        },
        {
            "id": "100084852637978",
            "count": 0,
            "name": "Người dùng facebook"
        },
        {
            "id": "100084980013051",
            "count": 0,
            "name": "Người dùng facebook"
        },
        {
            "id": "100085624261769",
            "count": 0,
            "name": "Người dùng facebook"
        },
        {
            "id": "100086280722638",
            "count": 0,
            "name": "Người dùng facebook"
        },
        {
            "id": "100086293245287",
            "count": 0,
            "name": "Người dùng facebook"
        },
        {
            "id": "100086985161146",
            "count": 0,
            "name": "Người dùng facebook"
        },
        {
            "id": "100087499030458",
            "count": 0,
            "name": "Người dùng facebook"
        },
        {
            "id": "100087627632878",
            "count": 0,
            "name": "Người dùng facebook"
        },
        {
            "id": "100087645395449",
            "count": 0,
            "name": "Người dùng facebook"
        },
        {
            "id": "100087941115166",
            "count": 0,
            "name": "Người dùng facebook"
        },
        {
            "id": "100088741953052",
            "count": 0,
            "name": "Người dùng facebook"
        },
        {
            "id": "100088873552113",
            "count": 0,
            "name": "Người dùng facebook"
        },
        {
            "id": "100088947065380",
            "count": 0,
            "name": "Người dùng facebook"
        },
        {
            "id": "100089336877077",
            "count": 0,
            "name": "Người dùng facebook"
        },
        {
            "id": "100089438408044",
            "count": 0,
            "name": "Người dùng facebook"
        },
        {
            "id": "100089974189493",
            "count": 0,
            "name": "Người dùng facebook"
        },
        {
            "id": "100090648552155",
            "count": 0,
            "name": "Người dùng facebook"
        },
        {
            "id": "100092614584832",
            "count": 0,
            "name": "Người dùng facebook"
        },
        {
            "id": "100094073404198",
            "count": 0,
            "name": "Người dùng facebook"
        },
        {
            "id": "100094104075713",
            "count": 0,
            "name": "Người dùng facebook"
        },
        {
            "id": "100094412376863",
            "count": 0,
            "name": "Người dùng facebook"
        }
    ],
    "day": [
        {
            "id": "100009288627141",
            "count": 0,
            "name": "Người dùng facebook"
        },
        {
            "id": "100013074420199",
            "count": 0,
            "name": "Người dùng facebook"
        },
        {
            "id": "100023250277879",
            "count": 0,
            "name": "Người dùng Facebook"
        },
        {
            "id": "100025340854489",
            "count": 0,
            "name": "Người dùng facebook"
        },
        {
            "id": "100025976982919",
            "count": 0,
            "name": "Người dùng facebook"
        },
        {
            "id": "100040922983131",
            "count": 0,
            "name": "Người dùng facebook"
        },
        {
            "id": "100041054234903",
            "count": 0,
            "name": "Người dùng facebook"
        },
        {
            "id": "100046262590054",
            "count": 0,
            "name": "Người dùng facebook"
        },
        {
            "id": "100046618612572",
            "count": 0,
            "name": "Người dùng facebook"
        },
        {
            "id": "100048452412222",
            "count": 0,
            "name": "Người dùng facebook"
        },
        {
            "id": "100048479196349",
            "count": 0,
            "name": "Người dùng facebook"
        },
        {
            "id": "100049664452631",
            "count": 0,
            "name": "Người dùng facebook"
        },
        {
            "id": "100049719559171",
            "count": 0,
            "name": "Người dùng facebook"
        },
        {
            "id": "100049735254389",
            "count": 0,
            "name": "Người dùng facebook"
        },
        {
            "id": "100049944961348",
            "count": 0,
            "name": "Người dùng facebook"
        },
        {
            "id": "100050203730446",
            "count": 0,
            "name": "Người dùng facebook"
        },
        {
            "id": "100051500760682",
            "count": 0,
            "name": "Người dùng facebook"
        },
        {
            "id": "100052484168838",
            "count": 0,
            "name": "Người dùng facebook"
        },
        {
            "id": "100053658735072",
            "count": 0,
            "name": "Người dùng facebook"
        },
        {
            "id": "100054387824870",
            "count": 0,
            "name": "Người dùng facebook"
        },
        {
            "id": "100055445830854",
            "count": 0,
            "name": "Người dùng facebook"
        },
        {
            "id": "100056063895388",
            "count": 0,
            "name": "Người dùng facebook"
        },
        {
            "id": "100056905673878",
            "count": 0,
            "name": "Người dùng facebook"
        },
        {
            "id": "100056908487439",
            "count": 0,
            "name": "Người dùng facebook"
        },
        {
            "id": "100057346640782",
            "count": 0,
            "name": "Người dùng facebook"
        },
        {
            "id": "100057469185744",
            "count": 0,
            "name": "Người dùng facebook"
        },
        {
            "id": "100058017127468",
            "count": 0,
            "name": "Người dùng facebook"
        },
        {
            "id": "100059293400126",
            "count": 0,
            "name": "Người dùng facebook"
        },
        {
            "id": "100059435633751",
            "count": 0,
            "name": "Người dùng facebook"
        },
        {
            "id": "100059650972916",
            "count": 0,
            "name": "Người dùng facebook"
        },
        {
            "id": "100059921825788",
            "count": 0,
            "name": "Người dùng facebook"
        },
        {
            "id": "100060160005306",
            "count": 0,
            "name": "Người dùng facebook"
        },
        {
            "id": "100060736756146",
            "count": 0,
            "name": "Người dùng facebook"
        },
        {
            "id": "100063144067332",
            "count": 0,
            "name": "Người dùng facebook"
        },
        {
            "id": "100063368597214",
            "count": 0,
            "name": "Người dùng facebook"
        },
        {
            "id": "100063530955135",
            "count": 0,
            "name": "Người dùng facebook"
        },
        {
            "id": "100063531206707",
            "count": 0,
            "name": "Người dùng facebook"
        },
        {
            "id": "100065106760629",
            "count": 0,
            "name": "Người dùng facebook"
        },
        {
            "id": "100066350868887",
            "count": 0,
            "name": "Người dùng facebook"
        },
        {
            "id": "100067327646975",
            "count": 0,
            "name": "Người dùng facebook"
        },
        {
            "id": "100067527685328",
            "count": 0,
            "name": "Người dùng facebook"
        },
        {
            "id": "100068259756683",
            "count": 0,
            "name": "Người dùng facebook"
        },
        {
            "id": "100069462471621",
            "count": 0,
            "name": "Người dùng facebook"
        },
        {
            "id": "100070217311047",
            "count": 0,
            "name": "Người dùng facebook"
        },
        {
            "id": "100070639362261",
            "count": 0,
            "name": "Người dùng facebook"
        },
        {
            "id": "100070889514699",
            "count": 0,
            "name": "Người dùng facebook"
        },
        {
            "id": "100070918685312",
            "count": 0,
            "name": "Người dùng facebook"
        },
        {
            "id": "100070993077260",
            "count": 0,
            "name": "Người dùng facebook"
        },
        {
            "id": "100071676530177",
            "count": 0,
            "name": "Người dùng facebook"
        },
        {
            "id": "100071878207269",
            "count": 0,
            "name": "Người dùng facebook"
        },
        {
            "id": "100072376201236",
            "count": 0,
            "name": "Người dùng facebook"
        },
        {
            "id": "100072476622464",
            "count": 0,
            "name": "Người dùng facebook"
        },
        {
            "id": "100072675626566",
            "count": 0,
            "name": "Người dùng facebook"
        },
        {
            "id": "100072736390649",
            "count": 0,
            "name": "Người dùng facebook"
        },
        {
            "id": "100072986970167",
            "count": 0,
            "name": "Người dùng facebook"
        },
        {
            "id": "100073308109648",
            "count": 0,
            "name": "Người dùng facebook"
        },
        {
            "id": "100073384754552",
            "count": 0,
            "name": "Người dùng facebook"
        },
        {
            "id": "100073458698273",
            "count": 0,
            "name": "Người dùng facebook"
        },
        {
            "id": "100073519582661",
            "count": 0,
            "name": "Người dùng facebook"
        },
        {
            "id": "100073681931859",
            "count": 0,
            "name": "Người dùng facebook"
        },
        {
            "id": "100074730408833",
            "count": 0,
            "name": "Người dùng facebook"
        },
        {
            "id": "100074731273232",
            "count": 0,
            "name": "Người dùng facebook"
        },
        {
            "id": "100074874152789",
            "count": 0,
            "name": "Người dùng facebook"
        },
        {
            "id": "100075049867323",
            "count": 0,
            "name": "Người dùng facebook"
        },
        {
            "id": "100075084227860",
            "count": 0,
            "name": "Người dùng facebook"
        },
        {
            "id": "100075146145340",
            "count": 0,
            "name": "Người dùng facebook"
        },
        {
            "id": "100075181744544",
            "count": 0,
            "name": "Người dùng facebook"
        },
        {
            "id": "100076926289765",
            "count": 0,
            "name": "Người dùng facebook"
        },
        {
            "id": "100077911120935",
            "count": 0,
            "name": "Người dùng facebook"
        },
        {
            "id": "100078312846000",
            "count": 0,
            "name": "Người dùng facebook"
        },
        {
            "id": "100078539427115",
            "count": 0,
            "name": "Người dùng facebook"
        },
        {
            "id": "100078562897868",
            "count": 0,
            "name": "Người dùng facebook"
        },
        {
            "id": "100078714319232",
            "count": 0,
            "name": "Người dùng facebook"
        },
        {
            "id": "100079138365262",
            "count": 0,
            "name": "Người dùng facebook"
        },
        {
            "id": "100079225460443",
            "count": 0,
            "name": "Người dùng facebook"
        },
        {
            "id": "100079264843097",
            "count": 0,
            "name": "Người dùng facebook"
        },
        {
            "id": "100079894541249",
            "count": 0,
            "name": "Người dùng facebook"
        },
        {
            "id": "100080066552735",
            "count": 0,
            "name": "Người dùng facebook"
        },
        {
            "id": "100080145905071",
            "count": 0,
            "name": "Người dùng facebook"
        },
        {
            "id": "100080229300189",
            "count": 0,
            "name": "Người dùng facebook"
        },
        {
            "id": "100080251070141",
            "count": 0,
            "name": "Người dùng facebook"
        },
        {
            "id": "100081168608728",
            "count": 0,
            "name": "Người dùng facebook"
        },
        {
            "id": "100081347157671",
            "count": 0,
            "name": "Người dùng facebook"
        },
        {
            "id": "100081540274688",
            "count": 0,
            "name": "Người dùng facebook"
        },
        {
            "id": "100082289148128",
            "count": 0,
            "name": "Người dùng facebook"
        },
        {
            "id": "100082754524557",
            "count": 0,
            "name": "Người dùng facebook"
        },
        {
            "id": "100083206190313",
            "count": 0,
            "name": "Người dùng facebook"
        },
        {
            "id": "100083708986199",
            "count": 0,
            "name": "Người dùng facebook"
        },
        {
            "id": "100083786662840",
            "count": 0,
            "name": "Người dùng facebook"
        },
        {
            "id": "100084136490078",
            "count": 0,
            "name": "Người dùng facebook"
        },
        {
            "id": "100084277832142",
            "count": 0,
            "name": "Người dùng facebook"
        },
        {
            "id": "100084509209404",
            "count": 0,
            "name": "Người dùng facebook"
        },
        {
            "id": "100084516589945",
            "count": 0,
            "name": "Người dùng facebook"
        },
        {
            "id": "100084735526565",
            "count": 0,
            "name": "Đỗ Nv Một"
        },
        {
            "id": "100084736032258",
            "count": 0,
            "name": "Người dùng facebook"
        },
        {
            "id": "100084852637978",
            "count": 0,
            "name": "Người dùng facebook"
        },
        {
            "id": "100084980013051",
            "count": 0,
            "name": "Người dùng facebook"
        },
        {
            "id": "100085624261769",
            "count": 0,
            "name": "Người dùng facebook"
        },
        {
            "id": "100086280722638",
            "count": 0,
            "name": "Người dùng facebook"
        },
        {
            "id": "100086293245287",
            "count": 0,
            "name": "Người dùng facebook"
        },
        {
            "id": "100086985161146",
            "count": 0,
            "name": "Người dùng facebook"
        },
        {
            "id": "100087499030458",
            "count": 0,
            "name": "Người dùng facebook"
        },
        {
            "id": "100087627632878",
            "count": 0,
            "name": "Người dùng facebook"
        },
        {
            "id": "100087645395449",
            "count": 0,
            "name": "Người dùng facebook"
        },
        {
            "id": "100087941115166",
            "count": 0,
            "name": "Người dùng facebook"
        },
        {
            "id": "100088741953052",
            "count": 0,
            "name": "Người dùng facebook"
        },
        {
            "id": "100088873552113",
            "count": 0,
            "name": "Người dùng facebook"
        },
        {
            "id": "100088947065380",
            "count": 0,
            "name": "Người dùng facebook"
        },
        {
            "id": "100089336877077",
            "count": 0,
            "name": "Người dùng facebook"
        },
        {
            "id": "100089438408044",
            "count": 0,
            "name": "Người dùng facebook"
        },
        {
            "id": "100089974189493",
            "count": 0,
            "name": "Người dùng facebook"
        },
        {
            "id": "100090648552155",
            "count": 0,
            "name": "Người dùng facebook"
        },
        {
            "id": "100092614584832",
            "count": 0,
            "name": "Người dùng facebook"
        },
        {
            "id": "100094073404198",
            "count": 0,
            "name": "Người dùng facebook"
        },
        {
            "id": "100094104075713",
            "count": 0,
            "name": "Người dùng facebook"
        },
        {
            "id": "100094412376863",
            "count": 0,
            "name": "Người dùng facebook"
        }
    ],
    "time": 3
}